logo_standardizer/__init__.py
logo_standardizer/logo_standardize.py
logo_standardizer-1.0.1.dist-info/LICENSE
logo_standardizer-1.0.1.dist-info/METADATA
logo_standardizer-1.0.1.dist-info/WHEEL
logo_standardizer-1.0.1.dist-info/top_level.txt
logo_standardizer-1.0.1.dist-info/RECORD
