Metadata-Version: 2.1
Name: logo-standardizer
Version: 1.0.1
Summary: Smart logo standardizer
Author: Mohammed Elsiddig (Jubii)
Author-email: mohammedjelsiddig@gmail.com
Keywords: python,logo,standardization,logo standardizer,logo resizer,logo standardize,resize,standardize
Classifier: License :: OSI Approved :: MIT License
Classifier: Intended Audience :: Developers
Classifier: Operating System :: OS Independent
Classifier: Programming Language :: Python :: 3
Requires-Python: >=3.6
License-File: LICENSE
Requires-Dist: opencv-python (==4.7.0.72)
Requires-Dist: Pillow (==9.0.0)
